{
    "domain": "djiservice.org",
    "owner": {},
    "source": [
        "DuckDuckGo-AU"
    ],
    "prevalence": 0.000301,
    "sites": 3,
    "subdomains": [
        "cdp-vg"
    ],
    "cnames": [],
    "fingerprinting": 0,
    "resources": [
        {
            "rule": "djiservice\\.org\\/sa\\.gif",
            "cookies": 0,
            "fingerprinting": 0,
            "subdomains": [
                "cdp-vg"
            ],
            "apis": {},
            "sites": 3,
            "prevalence": 0.000301,
            "cnames": [],
            "responseHashes": [
                "e3b0c44298fc1c149afbf4c8996fb92427ae41e4649b934ca495991b7852b855"
            ],
            "type": "Ping",
            "firstPartyCookies": {},
            "firstPartyCookiesSent": {},
            "exampleSites": [
                "dji.com",
                "store.dji.com",
                "www.dji.com"
            ]
        }
    ],
    "categories": [],
    "performance": {},
    "cookies": 0.0001,
    "topInitiators": [
        {
            "domain": "djiits.com",
            "prevalence": 0.9
        },
        {
            "domain": "djicdn.com",
            "prevalence": 0.1
        }
    ],
    "types": {
        "Ping": 3
    },
    "nameservers": [
        "ns-125.awsdns-15.com",
        "ns-1585.awsdns-06.co.uk",
        "ns-959.awsdns-55.net",
        "ns-1056.awsdns-04.org"
    ]
}