{
    "domain": "cherrytv.media",
    "owner": {},
    "source": [
        "DuckDuckGo-GB"
    ],
    "prevalence": 0.000603,
    "sites": 6,
    "subdomains": [
        "cdn77"
    ],
    "cnames": [],
    "fingerprinting": 0,
    "resources": [
        {
            "rule": "cherrytv\\.media\\/z2MGonDVkOnI3PLfIByaYd7F1wuOh2wyihRPY6WLVU6Myw3XJF7a8jj-L0oI5_JOza7SpAd8gmUPRF_CpetT_d7Tshp3L5Us",
            "cookies": 0,
            "fingerprinting": 0,
            "subdomains": [],
            "apis": {},
            "sites": 3,
            "prevalence": 0.000301,
            "cnames": [],
            "responseHashes": [
                "f462897b09b60e8f4fb8cfa2743f96f160c40015b121c8a53476ea239788d243"
            ],
            "type": "XHR",
            "firstPartyCookies": {},
            "firstPartyCookiesSent": {},
            "exampleSites": [
                "hobby.porn",
                "www.hentaicity.com",
                "www.pornrabbit.com"
            ]
        },
        {
            "rule": "cherrytv\\.media\\/files2577\\/10\\/369\\/3562\\/2\\.%20JessiQ_0830_1\\.mp4",
            "cookies": 0,
            "fingerprinting": 0,
            "subdomains": [
                "cdn77"
            ],
            "apis": {},
            "sites": 2,
            "prevalence": 0.000201,
            "cnames": [],
            "responseHashes": [],
            "type": "Media",
            "firstPartyCookies": {},
            "firstPartyCookiesSent": {},
            "exampleSites": [
                "hobby.porn",
                "www.pornrabbit.com"
            ]
        },
        {
            "rule": "cherrytv\\.media\\/zlmfgUgwt6OWFXRoDcmZ0vyCtZgEIx4oYLp9w_GNMTxdrxZ8Oo24OZD9wwr9x3yNy52SmGnmgCsuQJKg_luqCpmgcev_iIts",
            "cookies": 0.0001,
            "fingerprinting": 0,
            "subdomains": [],
            "apis": {},
            "sites": 2,
            "prevalence": 0.000201,
            "cnames": [],
            "responseHashes": [
                "c5c46e5c2431cb92af33297a687ae653d84761dcd2acd1aaa33776dc68adf164"
            ],
            "type": "XHR",
            "firstPartyCookies": {},
            "firstPartyCookiesSent": {},
            "exampleSites": [
                "spankbang.com",
                "la.spankbang.com"
            ]
        }
    ],
    "categories": [],
    "performance": {},
    "cookies": 0.000301,
    "topInitiators": [
        {
            "domain": "twinrdsrv.com",
            "prevalence": 0.4444444444444444
        },
        {
            "domain": "first party",
            "prevalence": 0.2222222222222222
        },
        {
            "domain": "eunow4u.com",
            "prevalence": 0.1111111111111111
        },
        {
            "domain": "magsrv.com",
            "prevalence": 0.1111111111111111
        },
        {
            "domain": "pemsrv.com",
            "prevalence": 0.1111111111111111
        }
    ],
    "types": {
        "XHR": 5,
        "Media": 2
    },
    "nameservers": [
        "marge.ns.cloudflare.com",
        "johnathan.ns.cloudflare.com"
    ]
}