{
    "domain": "bcbolt446c5271-a.akamaihd.net",
    "owner": {
        "name": "Akamai Technologies",
        "displayName": "Akamai",
        "privacyPolicy": "https://www.akamai.com/us/en/privacy-policies/",
        "url": "http://akamai.com"
    },
    "source": [
        "DuckDuckGo-DE"
    ],
    "prevalence": 0.000201,
    "sites": 2,
    "subdomains": [],
    "cnames": [],
    "fingerprinting": 0,
    "resources": [
        {
            "rule": "bcbolt446c5271-a\\.akamaihd\\.net\\/media\\/v1\\/pmp4\\/static\\/clear\\/1384193102001\\/3e1e23cb-cffe-4f41-abae-67581726b475\\/mid\\.mp4",
            "cookies": 0,
            "fingerprinting": 0,
            "subdomains": [],
            "apis": {},
            "sites": 2,
            "prevalence": 0.000201,
            "cnames": [],
            "responseHashes": [],
            "type": "Media",
            "firstPartyCookies": {},
            "firstPartyCookiesSent": {},
            "exampleSites": [
                "cisco.com",
                "www.cisco.com"
            ]
        },
        {
            "rule": "bcbolt446c5271-a\\.akamaihd\\.net\\/media\\/v1\\/pmp4\\/static\\/clear\\/1384193102001\\/3e1e23cb-cffe-4f41-abae-67581726b475\\/high\\.mp4",
            "cookies": 0,
            "fingerprinting": 0,
            "subdomains": [],
            "apis": {},
            "sites": 2,
            "prevalence": 0.000201,
            "cnames": [],
            "responseHashes": [],
            "type": "Media",
            "firstPartyCookies": {},
            "firstPartyCookiesSent": {},
            "exampleSites": [
                "cisco.com",
                "www.cisco.com"
            ]
        },
        {
            "rule": "bcbolt446c5271-a\\.akamaihd\\.net\\/media\\/v1\\/pmp4\\/static\\/clear\\/1384193102001\\/0d1fb7aa-f16f-475c-b63f-5a410154e956\\/e8280dca-ace1-4e1d-b54c-7a165308dcc0\\/main\\.mp4",
            "cookies": 0,
            "fingerprinting": 0,
            "subdomains": [],
            "apis": {},
            "sites": 2,
            "prevalence": 0.000201,
            "cnames": [],
            "responseHashes": [],
            "type": "Media",
            "firstPartyCookies": {},
            "firstPartyCookiesSent": {},
            "exampleSites": [
                "webex.com",
                "www.webex.com"
            ]
        },
        {
            "rule": "bcbolt446c5271-a\\.akamaihd\\.net\\/media\\/v1\\/pmp4\\/static\\/clear\\/1384193102001\\/a13fb498-e0b7-48f7-b482-a90ccb57521a\\/6bf803aa-a152-474b-9d85-72b443c1a01d\\/main\\.mp4",
            "cookies": 0,
            "fingerprinting": 0,
            "subdomains": [],
            "apis": {},
            "sites": 2,
            "prevalence": 0.000201,
            "cnames": [],
            "responseHashes": [],
            "type": "Media",
            "firstPartyCookies": {},
            "firstPartyCookiesSent": {},
            "exampleSites": [
                "webex.com",
                "www.webex.com"
            ]
        }
    ],
    "categories": [
        "CDN"
    ],
    "performance": {},
    "cookies": 0,
    "topInitiators": [
        {
            "domain": "first party",
            "prevalence": 1
        }
    ],
    "types": {
        "Media": 8
    },
    "nameservers": []
}