{
    "domain": "stepstone.de",
    "owner": {
        "name": "StepStone GmbH",
        "displayName": "StepStone"
    },
    "source": [
        "DuckDuckGo-DE"
    ],
    "prevalence": 0.000402,
    "sites": 4,
    "subdomains": [
        "www"
    ],
    "cnames": [],
    "fingerprinting": 1,
    "resources": [
        {
            "rule": "stepstone\\.de\\/viewlets\\/consent\\/consent-manager\\/stst-properties\\/assets-d2c0a8b0c03c4e28bd6326171a51dcbe\\/styles\\/core-content\\.css",
            "cookies": 0.000201,
            "fingerprinting": 0,
            "subdomains": [
                "www"
            ],
            "apis": {},
            "sites": 2,
            "prevalence": 0.000201,
            "cnames": [],
            "responseHashes": [
                "00f31bf51f088ba5895929bcab3fe4f2407712aaba16cc6d14795439d433591c"
            ],
            "type": "Stylesheet",
            "firstPartyCookies": {},
            "firstPartyCookiesSent": {},
            "exampleSites": [
                "gehalt.de",
                "www.gehaltsvergleich.com"
            ]
        },
        {
            "rule": "stepstone\\.de\\/viewlets\\/consent\\/consent-manager\\/stst-properties\\/assets-d2c0a8b0c03c4e28bd6326171a51dcbe\\/shared\\/active-vendors\\.json",
            "cookies": 0.000201,
            "fingerprinting": 0,
            "subdomains": [
                "www"
            ],
            "apis": {},
            "sites": 2,
            "prevalence": 0.000201,
            "cnames": [],
            "responseHashes": [
                "a83d8b19dd3e1797049c06e0cb4e4acdbb107eefb0a62712cf08e1ed92de99a4"
            ],
            "type": "XHR",
            "firstPartyCookies": {},
            "firstPartyCookiesSent": {},
            "exampleSites": [
                "gehalt.de",
                "www.gehaltsvergleich.com"
            ]
        }
    ],
    "categories": [],
    "performance": {},
    "cookies": 0.000402,
    "topInitiators": [
        {
            "domain": "first party",
            "prevalence": 0.6363636363636364
        },
        {
            "domain": "tiqcdn.com",
            "prevalence": 0.36363636363636365
        }
    ],
    "types": {
        "Stylesheet": 2,
        "XHR": 2
    },
    "nameservers": [
        "ns.domainnetwork.se",
        "ns2.domainnetwork.se",
        "ns3.domainnetwork.com"
    ]
}