{
    "domain": "safestatic.org",
    "owner": {},
    "source": [
        "DuckDuckGo-NO"
    ],
    "prevalence": 0.000502,
    "sites": 5,
    "subdomains": [
        "th"
    ],
    "cnames": [],
    "fingerprinting": 0,
    "resources": [
        {
            "rule": "safestatic\\.org\\/img\\/4732000\\/4732866\\/400x200\\/1\\.jpg",
            "cookies": 0,
            "fingerprinting": 0,
            "subdomains": [
                "th"
            ],
            "apis": {},
            "sites": 2,
            "prevalence": 0.000201,
            "cnames": [],
            "responseHashes": [
                "0e440d25d0483e8efc66152fe941398c308a6806c53a678f6dcb4f52ab0fbcf2"
            ],
            "type": "Image",
            "firstPartyCookies": {},
            "firstPartyCookiesSent": {},
            "exampleSites": [
                "her.porn",
                "onlybestporn.com"
            ]
        },
        {
            "rule": "safestatic\\.org\\/img\\/5910000\\/5910450\\/400x200\\/1\\.jpg",
            "cookies": 0,
            "fingerprinting": 0,
            "subdomains": [
                "th"
            ],
            "apis": {},
            "sites": 2,
            "prevalence": 0.000201,
            "cnames": [],
            "responseHashes": [
                "19293fd1c39f950c27ece071254978158ea5d42f6a762feb017a97794cf90ffb"
            ],
            "type": "Image",
            "firstPartyCookies": {},
            "firstPartyCookiesSent": {},
            "exampleSites": [
                "onlybestporn.com",
                "sos.xxx"
            ]
        }
    ],
    "categories": [],
    "performance": {},
    "cookies": 0,
    "topInitiators": [
        {
            "domain": "first party",
            "prevalence": 1
        }
    ],
    "types": {
        "Image": 4
    },
    "nameservers": [
        "donald.ns.cloudflare.com",
        "aron.ns.cloudflare.com"
    ]
}