{
    "domain": "toppfotball.no",
    "owner": {},
    "source": [
        "DuckDuckGo-NO"
    ],
    "prevalence": 0.001,
    "sites": 10,
    "subdomains": [
        "beta"
    ],
    "cnames": [],
    "fingerprinting": 0,
    "resources": [
        {
            "rule": "toppfotball\\.no\\/fonts\\/837215\\/835375DE00756140B\\.css",
            "cookies": 0,
            "fingerprinting": 0,
            "subdomains": [
                "beta"
            ],
            "apis": {},
            "sites": 10,
            "prevalence": 0.001,
            "cnames": [],
            "responseHashes": [
                "0e4e62c3354ccdb4c503971ec77f459e8cde2b49ab76e12743245db9daf44d6b"
            ],
            "type": "Stylesheet",
            "firstPartyCookies": {},
            "firstPartyCookiesSent": {},
            "exampleSites": [
                "lyn1896.no",
                "www.brann.no",
                "www.eliteserien.no",
                "www.fredrikstadfk.no",
                "www.glimt.no",
                "www.moldefk.no",
                "www.obos-ligaen.no",
                "www.odd.no",
                "www.rbk.no",
                "www.vikingfotball.no"
            ]
        }
    ],
    "categories": [],
    "performance": {},
    "cookies": 0,
    "topInitiators": [
        {
            "domain": "first party",
            "prevalence": 1
        }
    ],
    "types": {
        "Stylesheet": 10
    },
    "nameservers": [
        "zelda.ns.cloudflare.com",
        "bob.ns.cloudflare.com"
    ]
}