{
    "domain": "d1dwpx74eozflt.cloudfront.net",
    "owner": {
        "name": "Amazon Technologies, Inc.",
        "displayName": "Amazon.com",
        "privacyPolicy": "https://www.amazon.com/gp/help/customer/display.html?nodeId=468496",
        "url": "http://amazon.com"
    },
    "source": [
        "DuckDuckGo-US"
    ],
    "prevalence": 0.000178,
    "sites": 26,
    "subdomains": [],
    "cnames": [],
    "fingerprinting": 0,
    "resources": [
        {
            "rule": "d1dwpx74eozflt\\.cloudfront\\.net\\/t",
            "cookies": 0,
            "fingerprinting": 0,
            "subdomains": [],
            "apis": {},
            "sites": 17,
            "prevalence": 0.000116,
            "cnames": [],
            "responseHashes": [],
            "type": "Fetch",
            "firstPartyCookies": {},
            "firstPartyCookiesSent": {},
            "exampleSites": [
                "avecamourlingerie.com",
                "dazzledry.com",
                "heartstonefarm.com",
                "levtexhome.com",
                "peasedoors.com",
                "subimods.com",
                "topodesigns.com",
                "us.amazfit.com",
                "www.bartonwatchbands.com",
                "www.fmshobby.com",
                "www.hanksbelts.com",
                "www.harveywoodworking.com",
                "www.luglife.com",
                "www.rowecasaorganics.com",
                "www.trxtraining.com",
                "www.vicicollection.com",
                "www.woolly.clothing"
            ]
        }
    ],
    "categories": [
        "CDN"
    ],
    "performance": {},
    "cookies": 0,
    "topInitiators": [
        {
            "domain": "first party",
            "prevalence": 1
        }
    ],
    "types": {
        "Fetch": 17
    },
    "nameservers": [
        "ns-1443.awsdns-52.org",
        "ns-1583.awsdns-05.co.uk",
        "ns-476.awsdns-59.com",
        "ns-727.awsdns-26.net"
    ]
}