{
    "domain": "onlinesizing.bike",
    "owner": {},
    "source": [
        "DuckDuckGo-US"
    ],
    "prevalence": 0.0000205,
    "sites": 3,
    "subdomains": [
        "widgets",
        "api"
    ],
    "cnames": [],
    "fingerprinting": 1,
    "resources": [
        {
            "rule": "onlinesizing\\.bike\\/loader\\.js",
            "cookies": 0,
            "fingerprinting": 0,
            "subdomains": [
                "widgets"
            ],
            "apis": {},
            "sites": 3,
            "prevalence": 0.0000205,
            "cnames": [],
            "responseHashes": [
                "da77866ed62952dc1b5bbd02bf495dbb2dcaba94eb3e0785483e5d50f607e6fe"
            ],
            "type": "Script",
            "firstPartyCookies": {},
            "firstPartyCookiesSent": {},
            "exampleSites": [
                "koga.com",
                "www.merida-bikes.com",
                "www.scott-sports.com"
            ]
        },
        {
            "rule": "onlinesizing\\.bike\\/v2-16-5\\/launcher\\/",
            "cookies": 0,
            "fingerprinting": 0,
            "subdomains": [
                "widgets"
            ],
            "apis": {},
            "sites": 3,
            "prevalence": 0.0000205,
            "cnames": [],
            "responseHashes": [
                "e52302da46752542a8ca5c45c50c259e56b9e9e68d2418ba1563ad37fcd1e7f3"
            ],
            "type": "Document",
            "firstPartyCookies": {},
            "firstPartyCookiesSent": {},
            "exampleSites": [
                "koga.com",
                "www.merida-bikes.com",
                "www.scott-sports.com"
            ]
        },
        {
            "rule": "onlinesizing\\.bike\\/v2-16-5\\/static\\/js\\/3282\\.63c6c9fb\\.js",
            "cookies": 0,
            "fingerprinting": 0,
            "subdomains": [
                "widgets"
            ],
            "apis": {},
            "sites": 3,
            "prevalence": 0.0000205,
            "cnames": [],
            "responseHashes": [
                "e7e278cf6f62f199e7e77dce8e44c405f97925c69f5dc8396cc084aa3df05543"
            ],
            "type": "Script",
            "firstPartyCookies": {},
            "firstPartyCookiesSent": {},
            "exampleSites": [
                "koga.com",
                "www.merida-bikes.com",
                "www.scott-sports.com"
            ]
        },
        {
            "rule": "onlinesizing\\.bike\\/v2-16-5\\/static\\/js\\/3398\\.7eed40e5\\.js",
            "cookies": 0,
            "fingerprinting": 0,
            "subdomains": [
                "widgets"
            ],
            "apis": {},
            "sites": 3,
            "prevalence": 0.0000205,
            "cnames": [],
            "responseHashes": [
                "24dedb08c21e93aedd3a1a8a6c3320df648bd3fbb1103fc301f8a72d14980c14"
            ],
            "type": "Script",
            "firstPartyCookies": {},
            "firstPartyCookiesSent": {},
            "exampleSites": [
                "koga.com",
                "www.merida-bikes.com",
                "www.scott-sports.com"
            ]
        },
        {
            "rule": "onlinesizing\\.bike\\/v2-16-5\\/static\\/js\\/1313\\.70a096f6\\.js",
            "cookies": 0,
            "fingerprinting": 0,
            "subdomains": [
                "widgets"
            ],
            "apis": {},
            "sites": 3,
            "prevalence": 0.0000205,
            "cnames": [],
            "responseHashes": [
                "d01636a8cf048eebfae39c99565a2ecdf9b2d0948bf0dd62f4bf213d270f10a4"
            ],
            "type": "Script",
            "firstPartyCookies": {},
            "firstPartyCookiesSent": {},
            "exampleSites": [
                "koga.com",
                "www.merida-bikes.com",
                "www.scott-sports.com"
            ]
        },
        {
            "rule": "onlinesizing\\.bike\\/v2-16-5\\/static\\/js\\/9854\\.e083c25b\\.js",
            "cookies": 0,
            "fingerprinting": 0,
            "subdomains": [
                "widgets"
            ],
            "apis": {},
            "sites": 3,
            "prevalence": 0.0000205,
            "cnames": [],
            "responseHashes": [
                "36ee2949dce4409fe7204493ea78942132a546105c707e038fa85d727271bd9c"
            ],
            "type": "Script",
            "firstPartyCookies": {},
            "firstPartyCookiesSent": {},
            "exampleSites": [
                "koga.com",
                "www.merida-bikes.com",
                "www.scott-sports.com"
            ]
        },
        {
            "rule": "onlinesizing\\.bike\\/v2-16-5\\/static\\/js\\/5482\\.319d0814\\.js",
            "cookies": 0,
            "fingerprinting": 1,
            "subdomains": [
                "widgets"
            ],
            "apis": {
                "window.localStorage": 3
            },
            "sites": 3,
            "prevalence": 0.0000205,
            "cnames": [],
            "responseHashes": [
                "56bca8dc714702e82fe239d254560a66cff7cc8e73451adf0eae2214167acd2b"
            ],
            "type": "Script",
            "firstPartyCookies": {},
            "firstPartyCookiesSent": {},
            "exampleSites": [
                "koga.com",
                "www.merida-bikes.com",
                "www.scott-sports.com"
            ]
        },
        {
            "rule": "onlinesizing\\.bike\\/v2-16-5\\/static\\/js\\/8911\\.32dd6074\\.js",
            "cookies": 0,
            "fingerprinting": 0,
            "subdomains": [
                "widgets"
            ],
            "apis": {},
            "sites": 3,
            "prevalence": 0.0000205,
            "cnames": [],
            "responseHashes": [
                "151b5479357dbab96044c605aea6c2e2549a9e08790f0132e631e75fdf1801e4"
            ],
            "type": "Script",
            "firstPartyCookies": {},
            "firstPartyCookiesSent": {},
            "exampleSites": [
                "koga.com",
                "www.merida-bikes.com",
                "www.scott-sports.com"
            ]
        },
        {
            "rule": "onlinesizing\\.bike\\/v2-16-5\\/static\\/js\\/6330\\.3f75ba2e\\.js",
            "cookies": 0,
            "fingerprinting": 0,
            "subdomains": [
                "widgets"
            ],
            "apis": {},
            "sites": 3,
            "prevalence": 0.0000205,
            "cnames": [],
            "responseHashes": [
                "cb033bad38c8a2ab7f12f6735c9710c55dfa1df3830d51d322d95965a81398ba"
            ],
            "type": "Script",
            "firstPartyCookies": {},
            "firstPartyCookiesSent": {},
            "exampleSites": [
                "koga.com",
                "www.merida-bikes.com",
                "www.scott-sports.com"
            ]
        },
        {
            "rule": "onlinesizing\\.bike\\/v2-16-5\\/static\\/js\\/launcher\\.d5ec3971\\.js",
            "cookies": 0,
            "fingerprinting": 0,
            "subdomains": [
                "widgets"
            ],
            "apis": {},
            "sites": 3,
            "prevalence": 0.0000205,
            "cnames": [],
            "responseHashes": [
                "b62213cea61aa7d89d4a43cf60da412875039849d4c6bb4744621b88e57ab081"
            ],
            "type": "Script",
            "firstPartyCookies": {},
            "firstPartyCookiesSent": {},
            "exampleSites": [
                "koga.com",
                "www.merida-bikes.com",
                "www.scott-sports.com"
            ]
        },
        {
            "rule": "onlinesizing\\.bike\\/v2-16-5\\/static\\/js\\/i18n-5\\.f37c91ea\\.chunk\\.js",
            "cookies": 0,
            "fingerprinting": 0,
            "subdomains": [
                "widgets"
            ],
            "apis": {},
            "sites": 2,
            "prevalence": 0.0000137,
            "cnames": [],
            "responseHashes": [
                "f36de055541d4ef931ad4085d25c6a2dc38cada0bff8aeb5be0dd16d347751a2"
            ],
            "type": "Script",
            "firstPartyCookies": {},
            "firstPartyCookiesSent": {},
            "exampleSites": [
                "koga.com",
                "www.merida-bikes.com"
            ]
        },
        {
            "rule": "onlinesizing\\.bike\\/v16\\/login",
            "cookies": 0,
            "fingerprinting": 0,
            "subdomains": [
                "api"
            ],
            "apis": {},
            "sites": 3,
            "prevalence": 0.0000205,
            "cnames": [],
            "responseHashes": [
                "3d23d39a30bb7323f8ccfd64c52cf286138fba4f83e78f7edcf66703b7c23aaa"
            ],
            "type": "Fetch",
            "firstPartyCookies": {},
            "firstPartyCookiesSent": {},
            "exampleSites": [
                "koga.com",
                "www.merida-bikes.com",
                "www.scott-sports.com"
            ]
        },
        {
            "rule": "onlinesizing\\.bike\\/v16\\/login",
            "cookies": 0,
            "fingerprinting": 0,
            "subdomains": [
                "api"
            ],
            "apis": {},
            "sites": 3,
            "prevalence": 0.0000205,
            "cnames": [],
            "responseHashes": [],
            "type": "Preflight",
            "firstPartyCookies": {},
            "firstPartyCookiesSent": {},
            "exampleSites": [
                "koga.com",
                "www.merida-bikes.com",
                "www.scott-sports.com"
            ]
        },
        {
            "rule": "onlinesizing\\.bike\\/v16\\/widgets",
            "cookies": 0,
            "fingerprinting": 0,
            "subdomains": [
                "api"
            ],
            "apis": {},
            "sites": 3,
            "prevalence": 0.0000205,
            "cnames": [],
            "responseHashes": [],
            "type": "Preflight",
            "firstPartyCookies": {},
            "firstPartyCookiesSent": {},
            "exampleSites": [
                "koga.com",
                "www.merida-bikes.com",
                "www.scott-sports.com"
            ]
        },
        {
            "rule": "onlinesizing\\.bike\\/v16\\/widgets",
            "cookies": 0,
            "fingerprinting": 0,
            "subdomains": [
                "api"
            ],
            "apis": {},
            "sites": 3,
            "prevalence": 0.0000205,
            "cnames": [],
            "responseHashes": [
                "a7449251c42c73b042d64415755fe9edb7922ff81ffd83a711841d1488d187bc",
                "24855671d0b650824e9da29d0833b0328e589ae99ad93751ff4269e40a11e882"
            ],
            "type": "Fetch",
            "firstPartyCookies": {},
            "firstPartyCookiesSent": {},
            "exampleSites": [
                "koga.com",
                "www.merida-bikes.com",
                "www.scott-sports.com"
            ]
        }
    ],
    "categories": [],
    "performance": {},
    "cookies": 0,
    "topInitiators": [
        {
            "domain": "first party",
            "prevalence": 0.6666666666666666
        },
        {
            "domain": "usercentrics.eu",
            "prevalence": 0.3333333333333333
        }
    ],
    "types": {
        "Script": 29,
        "Document": 3,
        "Fetch": 6,
        "Preflight": 6
    },
    "nameservers": [
        "ns3.routing.net",
        "ns1.routing.net",
        "ns2.routing.net"
    ]
}