{
    "domain": "swiss.com.edgekey.net",
    "owner": {
        "name": "Akamai Technologies",
        "displayName": "Akamai",
        "privacyPolicy": "https://www.akamai.com/us/en/privacy-policies/",
        "url": "http://akamai.com"
    },
    "source": [
        "DuckDuckGo-US"
    ],
    "prevalence": 0.0000137,
    "sites": 2,
    "subdomains": [
        "api.travelid"
    ],
    "cnames": [
        {
            "original": "api.travelid.swiss.com",
            "resolved": "api.travelid.swiss.com.edgekey.net"
        }
    ],
    "fingerprinting": 0,
    "resources": [
        {
            "rule": "swiss\\.com\\.edgekey\\.net\\/v1\\/user\\/me\\/loginstatus",
            "cookies": 0.0000137,
            "fingerprinting": 0,
            "subdomains": [
                "api.travelid"
            ],
            "apis": {},
            "sites": 2,
            "prevalence": 0.0000137,
            "cnames": [
                {
                    "original": "api.travelid.swiss.com",
                    "resolved": "api.travelid.swiss.com.edgekey.net"
                }
            ],
            "responseHashes": [
                "481c20ff7667e800b92bfd77670f9f751d2165eb7f2e315ca7c02467d528e90f"
            ],
            "type": "XHR",
            "firstPartyCookies": {},
            "firstPartyCookiesSent": {},
            "exampleSites": [
                "swiss.com",
                "www.swiss.com"
            ]
        }
    ],
    "categories": [],
    "performance": {},
    "cookies": 0.0000137,
    "types": {
        "XHR": 2
    },
    "nameservers": []
}